ClauseStat/__init__.py
ClauseStat/sqlclausestat.py
ClauseStatistics_pavanjahagirdar-0.0.2.dist-info/LICENSE
ClauseStatistics_pavanjahagirdar-0.0.2.dist-info/METADATA
ClauseStatistics_pavanjahagirdar-0.0.2.dist-info/WHEEL
ClauseStatistics_pavanjahagirdar-0.0.2.dist-info/top_level.txt
ClauseStatistics_pavanjahagirdar-0.0.2.dist-info/RECORD
