Metadata-Version: 2.1
Name: ClauseStatistics-pavanjahagirdar
Version: 0.0.2
Summary: Statistics of Clause
Home-page: https://github.com/pavanjahagirdar/ClauseStatistics
Author: pavanjahagirdar
Author-email: pavanjahagirdar7@gmail.com
Project-URL: Bug Tracker, https://github.com/pavanjahagirdar/ClauseStatistics/issues
Classifier: Programming Language :: Python :: 3
Classifier: License :: OSI Approved :: MIT License
Classifier: Operating System :: OS Independent
Requires-Python: >=3.7
License-File: LICENSE
Requires-Dist: numpy
Requires-Dist: tqdm
